{
    "name": "Atlas Kos - Payment Notification",
    "nodes": [
        {
            "parameters": {
                "httpMethod": "POST",
                "path": "payment-notification",
                "responseMode": "responseNode",
                "options": {}
            },
            "id": "webhook-trigger",
            "name": "Webhook Trigger",
            "type": "n8n-nodes-base.webhook",
            "typeVersion": 2,
            "position": [
                250,
                300
            ],
            "webhookId": "payment-notification"
        },
        {
            "parameters": {
                "conditions": {
                    "options": {
                        "caseSensitive": true,
                        "leftValue": "",
                        "typeValidation": "strict"
                    },
                    "conditions": [
                        {
                            "id": "condition-lunas",
                            "leftValue": "={{ $json.status }}",
                            "rightValue": "LUNAS",
                            "operator": {
                                "type": "string",
                                "operation": "equals"
                            }
                        }
                    ],
                    "combinator": "and"
                },
                "options": {}
            },
            "id": "if-status",
            "name": "Check Status",
            "type": "n8n-nodes-base.if",
            "typeVersion": 2,
            "position": [
                470,
                300
            ]
        },
        {
            "parameters": {
                "assignments": {
                    "assignments": [
                        {
                            "id": "phone",
                            "name": "phone",
                            "value": "={{ $json.noHp.startsWith('0') ? '62' + $json.noHp.substring(1) : $json.noHp }}",
                            "type": "string"
                        },
                        {
                            "id": "message",
                            "name": "message",
                            "value": "✅ *Pembayaran Dikonfirmasi*\n\n{{ $json.message }}\n\nTerima kasih telah melakukan pembayaran tepat waktu.\n\n_Atlas Kos Management_",
                            "type": "string"
                        },
                        {
                            "id": "status",
                            "name": "status",
                            "value": "={{ $json.status }}",
                            "type": "string"
                        }
                    ]
                },
                "options": {}
            },
            "id": "format-lunas",
            "name": "Format Message (Lunas)",
            "type": "n8n-nodes-base.set",
            "typeVersion": 3.4,
            "position": [
                690,
                200
            ]
        },
        {
            "parameters": {
                "assignments": {
                    "assignments": [
                        {
                            "id": "phone",
                            "name": "phone",
                            "value": "={{ $json.noHp.startsWith('0') ? '62' + $json.noHp.substring(1) : $json.noHp }}",
                            "type": "string"
                        },
                        {
                            "id": "message",
                            "name": "message",
                            "value": "❌ *Pembayaran Ditolak*\n\n{{ $json.message }}\n\nSilakan upload ulang bukti pembayaran yang valid.\n\n_Atlas Kos Management_",
                            "type": "string"
                        },
                        {
                            "id": "status",
                            "name": "status",
                            "value": "={{ $json.status }}",
                            "type": "string"
                        }
                    ]
                },
                "options": {}
            },
            "id": "format-ditolak",
            "name": "Format Message (Ditolak)",
            "type": "n8n-nodes-base.set",
            "typeVersion": 3.4,
            "position": [
                690,
                400
            ]
        },
        {
            "parameters": {
                "method": "POST",
                "url": "https://api.fonnte.com/send",
                "sendHeaders": true,
                "headerParameters": {
                    "parameters": [
                        {
                            "name": "Authorization",
                            "value": "={{ $env.FONNTE_API_KEY }}"
                        }
                    ]
                },
                "sendBody": true,
                "specifyBody": "json",
                "jsonBody": "={\n  \"target\": \"{{ $json.phone }}\",\n  \"message\": \"{{ $json.message }}\",\n  \"countryCode\": \"62\"\n}",
                "options": {}
            },
            "id": "send-wa-lunas",
            "name": "Send WhatsApp (Lunas)",
            "type": "n8n-nodes-base.httpRequest",
            "typeVersion": 4.2,
            "position": [
                910,
                200
            ]
        },
        {
            "parameters": {
                "method": "POST",
                "url": "https://api.fonnte.com/send",
                "sendHeaders": true,
                "headerParameters": {
                    "parameters": [
                        {
                            "name": "Authorization",
                            "value": "={{ $env.FONNTE_API_KEY }}"
                        }
                    ]
                },
                "sendBody": true,
                "specifyBody": "json",
                "jsonBody": "={\n  \"target\": \"{{ $json.phone }}\",\n  \"message\": \"{{ $json.message }}\",\n  \"countryCode\": \"62\"\n}",
                "options": {}
            },
            "id": "send-wa-ditolak",
            "name": "Send WhatsApp (Ditolak)",
            "type": "n8n-nodes-base.httpRequest",
            "typeVersion": 4.2,
            "position": [
                910,
                400
            ]
        },
        {
            "parameters": {
                "respondWith": "json",
                "responseBody": "={\n  \"success\": true,\n  \"message\": \"Notification sent\",\n  \"status\": \"{{ $json.status }}\"\n}",
                "options": {}
            },
            "id": "response-success",
            "name": "Response Success",
            "type": "n8n-nodes-base.respondToWebhook",
            "typeVersion": 1.1,
            "position": [
                1130,
                300
            ]
        },
        {
            "parameters": {
                "respondWith": "json",
                "responseBody": "={\n  \"success\": false,\n  \"error\": \"{{ $json.error }}\"\n}",
                "options": {
                    "responseCode": 500
                }
            },
            "id": "response-error",
            "name": "Response Error",
            "type": "n8n-nodes-base.respondToWebhook",
            "typeVersion": 1.1,
            "position": [
                1130,
                500
            ]
        },
        {
            "parameters": {
                "assignments": {
                    "assignments": [
                        {
                            "id": "error",
                            "name": "error",
                            "value": "={{ $json.message || 'Unknown error occurred' }}",
                            "type": "string"
                        }
                    ]
                },
                "options": {}
            },
            "id": "catch-error",
            "name": "Handle Error",
            "type": "n8n-nodes-base.set",
            "typeVersion": 3.4,
            "position": [
                910,
                500
            ]
        }
    ],
    "connections": {
        "Webhook Trigger": {
            "main": [
                [
                    {
                        "node": "Check Status",
                        "type": "main",
                        "index": 0
                    }
                ]
            ]
        },
        "Check Status": {
            "main": [
                [
                    {
                        "node": "Format Message (Lunas)",
                        "type": "main",
                        "index": 0
                    }
                ],
                [
                    {
                        "node": "Format Message (Ditolak)",
                        "type": "main",
                        "index": 0
                    }
                ]
            ]
        },
        "Format Message (Lunas)": {
            "main": [
                [
                    {
                        "node": "Send WhatsApp (Lunas)",
                        "type": "main",
                        "index": 0
                    }
                ]
            ]
        },
        "Format Message (Ditolak)": {
            "main": [
                [
                    {
                        "node": "Send WhatsApp (Ditolak)",
                        "type": "main",
                        "index": 0
                    }
                ]
            ]
        },
        "Send WhatsApp (Lunas)": {
            "main": [
                [
                    {
                        "node": "Response Success",
                        "type": "main",
                        "index": 0
                    }
                ]
            ]
        },
        "Send WhatsApp (Ditolak)": {
            "main": [
                [
                    {
                        "node": "Response Success",
                        "type": "main",
                        "index": 0
                    }
                ]
            ]
        },
        "Handle Error": {
            "main": [
                [
                    {
                        "node": "Response Error",
                        "type": "main",
                        "index": 0
                    }
                ]
            ]
        }
    },
    "settings": {
        "executionOrder": "v1",
        "saveManualExecutions": true,
        "callerPolicy": "workflowsFromSameOwner",
        "errorWorkflow": ""
    },
    "staticData": null,
    "meta": {
        "instanceId": "atlas-kos-instance"
    },
    "pinData": {},
    "tags": [
        {
            "id": "atlas-kos",
            "name": "Atlas Kos"
        }
    ]
}